nomad_tajine_plugin/__init__.py
nomad_tajine_plugin/utils.py
nomad_tajine_plugin/apps/__init__.py
nomad_tajine_plugin/example_uploads/__init__.py
nomad_tajine_plugin/example_uploads/example/README.md
nomad_tajine_plugin/example_uploads/example/tajine.archive.yaml
nomad_tajine_plugin/example_uploads/example/ingredients/all-purpose_flour.archive.yaml
nomad_tajine_plugin/example_uploads/example/ingredients/bone-in_skin-on_chicken_thighs.archive.yaml
nomad_tajine_plugin/example_uploads/example/ingredients/carrots.archive.yaml
nomad_tajine_plugin/example_uploads/example/ingredients/cayenne_pepper.archive.yaml
nomad_tajine_plugin/example_uploads/example/ingredients/chicken_broth.archive.yaml
nomad_tajine_plugin/example_uploads/example/ingredients/fresh_cilantro_leaves.archive.yaml
nomad_tajine_plugin/example_uploads/example/ingredients/garlic.archive.yaml
nomad_tajine_plugin/example_uploads/example/ingredients/greek_cracked_green_olives.archive.yaml
nomad_tajine_plugin/example_uploads/example/ingredients/ground_black_pepper.archive.yaml
nomad_tajine_plugin/example_uploads/example/ingredients/ground_cinnamon.archive.yaml
nomad_tajine_plugin/example_uploads/example/ingredients/ground_coriander.archive.yaml
nomad_tajine_plugin/example_uploads/example/ingredients/ground_cumin.archive.yaml
nomad_tajine_plugin/example_uploads/example/ingredients/ground_ginger.archive.yaml
nomad_tajine_plugin/example_uploads/example/ingredients/honey.archive.yaml
nomad_tajine_plugin/example_uploads/example/ingredients/large_yellow_onion.archive.yaml
nomad_tajine_plugin/example_uploads/example/ingredients/lemon.archive.yaml
nomad_tajine_plugin/example_uploads/example/ingredients/olive_oil.archive.yaml
nomad_tajine_plugin/example_uploads/example/ingredients/paprika.archive.yaml
nomad_tajine_plugin/example_uploads/example/ingredients/salt.archive.yaml
nomad_tajine_plugin/parsers/__init__.py
nomad_tajine_plugin/parsers/parser.py
nomad_tajine_plugin/schema_packages/__init__.py
nomad_tajine_plugin-1.3.1.dist-info/licenses/LICENSE
nomad_tajine_plugin-1.3.1.dist-info/METADATA
nomad_tajine_plugin-1.3.1.dist-info/WHEEL
nomad_tajine_plugin-1.3.1.dist-info/entry_points.txt
nomad_tajine_plugin-1.3.1.dist-info/top_level.txt
nomad_tajine_plugin-1.3.1.dist-info/RECORD
