Metadata-Version: 2.4
Name: nomad-tajine-plugin
Version: 1.3.1
Summary: An example plugin showing how NOMAD can be used outside of material science for curating food recipes.
Author-email: Hampus Näsström <hampus.naesstroem@physik.hu-berlin.de>, FAIRmat <fairmat@physik.hu-berlin.de>
Maintainer-email: Hampus Näsström <hampus.naesstroem@physik.hu-berlin.de>, FAIRmat <fairmat@physik.hu-berlin.de>
License: 
Project-URL: Repository, https://github.com/FAIRmat-NFDI/nomad-tajine-plugin
Project-URL: Homepage, https://fairmat-nfdi.github.io/nomad-tajine-plugin/
Project-URL: Bug Tracker, https://github.com/FAIRmat-NFDI/nomad-tajine-plugin/issues
Project-URL: Documentation, https://fairmat-nfdi.github.io/nomad-tajine-plugin/
Classifier: Intended Audience :: Developers
Classifier: Operating System :: OS Independent
Classifier: Programming Language :: Python
Classifier: Programming Language :: Python :: 3.10
Classifier: Programming Language :: Python :: 3.11
Classifier: Programming Language :: Python :: 3.12
Classifier: License :: OSI Approved :: MIT License
Requires-Python: >=3.10
License-File: LICENSE
Requires-Dist: nomad-lab>=1.3.0
Requires-Dist: python-magic-bin; sys_platform == "win32"
Requires-Dist: rapidfuzz
Provides-Extra: dev
Requires-Dist: ruff; extra == "dev"
Requires-Dist: pytest; extra == "dev"
Requires-Dist: structlog; extra == "dev"
Requires-Dist: nomad-docs; extra == "dev"
Requires-Dist: mkdocs; extra == "dev"
Requires-Dist: mkdocs-material>=8.1.1; extra == "dev"
Requires-Dist: pymdown-extensions; extra == "dev"
Requires-Dist: mkdocs-click; extra == "dev"
Requires-Dist: mkdocs-macros-plugin; extra == "dev"
Dynamic: license-file
